dynodoc/__init__.py
dynodoc/dynodoc.py
dynodoc-0.1.dist-info/DESCRIPTION.rst
dynodoc-0.1.dist-info/METADATA
dynodoc-0.1.dist-info/RECORD
dynodoc-0.1.dist-info/WHEEL
dynodoc-0.1.dist-info/entry_points.txt
dynodoc-0.1.dist-info/metadata.json
dynodoc-0.1.dist-info/top_level.txt
